{"0.0.11": ["Addisu Z. Taddese", "addisuzt@intrinsic.ai"], "0.0.10": ["Addisu Z. Taddese", "addisuzt@intrinsic.ai"], "0.0.9": ["Addisu Z. Taddese", "addisuzt@intrinsic.ai"], "0.0.8": ["Addisu Z. Taddese", "addisuzt@intrinsic.ai"], "0.0.7": ["Addisu Z. Taddese", "addisuzt@intrinsic.ai"], "0.0.6": ["Addisu Z. Taddese", "addisuzt@intrinsic.ai"], "0.0.5": ["Addisu Z. Taddese", "addisuzt@intrinsic.ai"], "0.0.4": ["Addisu Z. Taddese", "addisuzt@intrinsic.ai"], "0.0.3": ["Addisu Z. Taddese", "addisuzt@intrinsic.ai"], "0.0.2": ["Addisu Z. Taddese", "addisuzt@intrinsic.ai"]}